shai_python/__init__.py
shai_python/config.py
shai_python/config.template.yaml
shai_python/main.py
shai_python/strings.py
shai_python-0.1.8.dist-info/METADATA
shai_python-0.1.8.dist-info/WHEEL
shai_python-0.1.8.dist-info/entry_points.txt
shai_python-0.1.8.dist-info/RECORD
