Metadata-Version: 2.4
Name: shai-python
Version: 0.1.8
Summary: AI-powered shell command generator using LLM models
Author-email: zonghai <zonghai@gmail.com>
License: MIT
Keywords: ai,cli,command-generator,llm,shell
Classifier: Development Status :: 3 - Alpha
Classifier: Environment :: Console
Classifier: Intended Audience :: Developers
Classifier: License :: OSI Approved :: MIT License
Classifier: Programming Language :: Python :: 3
Classifier: Programming Language :: Python :: 3.10
Classifier: Programming Language :: Python :: 3.11
Classifier: Programming Language :: Python :: 3.12
Classifier: Programming Language :: Python :: 3.13
Requires-Python: >=3.10
Requires-Dist: psutil>=7.2.2
Requires-Dist: pydantic-ai>=1.47.0
Requires-Dist: yaspin>=3.4.0
Provides-Extra: dev
Requires-Dist: black>=24.0.0; extra == 'dev'
Requires-Dist: mypy>=1.8.0; extra == 'dev'
Requires-Dist: pytest-asyncio>=0.24.0; extra == 'dev'
Requires-Dist: pytest>=8.0.0; extra == 'dev'
Requires-Dist: ruff>=0.4.0; extra == 'dev'
